data/__init__.py
data/doxygen-awesome-darkmode-toggle.js
data/doxygen-awesome-sidebar-only-darkmode-toggle.css
data/doxygen-awesome-sidebar-only.css
data/doxygen-awesome.css
data/doxygen.awesome.cfg
data/doxygen.private.cfg
data/doxygen.public.cfg
data/doxygen_footer.html
data/doxygen_header.awesome.html
data/doxygen_header.html
data/doxygen_layout.xml
data/doxygen_stylesheet.css
data/idv_doxyfilter_sv.pl
data/mio.toml
data/plantuml.jar
mio/__init__.py
mio/__main__.py
mio/cache.py
mio/cfg.py
mio/clean.py
mio/cli.py
mio/common.py
mio/cov.py
mio/doctor.py
mio/dox.py
mio/eal.py
mio/help_text.py
mio/init.py
mio/install.py
mio/main.py
mio/new.py
mio/publish.py
mio/regr.py
mio/results.py
mio/sim.py
mio/user.py
templates/LICENSE_solderpad_v2p1.md
templates/__init__.py
templates/dv_ip.yml
templates/interactive_results.html.j2
templates/mdc.flist.j2
templates/mdc.mflist.j2
templates/mio.toml
templates/project_gitignore
templates/qst.flist.j2
templates/qst.mflist.j2
templates/regression_results.html.j2
templates/riv.flist.j2
templates/riv.mflist.j2
templates/rtl_ip.yml
templates/sim_gitignore
templates/ts.yml.j2
templates/vcs.flist.j2
templates/vcs.mflist.j2
templates/viv.flist.j2
templates/viv.mflist.j2
templates/viv.prj.j2
templates/vivado_ip.yml
templates/xcl.flist.j2
templates/xcl.mflist.j2
mio_cli-1.3.10.dist-info/LICENSE
mio_cli-1.3.10.dist-info/METADATA
mio_cli-1.3.10.dist-info/WHEEL
mio_cli-1.3.10.dist-info/entry_points.txt
mio_cli-1.3.10.dist-info/top_level.txt
mio_cli-1.3.10.dist-info/RECORD
