Metadata-Version: 2.1
Name: mio-cli
Version: 1.3.10
Summary: The Moore.io Command Line Interface (CLI) Client is a toolchain for front-end engineering of FPGA/ASIC projects.
Home-page: https://datum-technology-corporation.github.io/mio_cli_client/
Author: Datum Technology Corporation
Author-email: mio@datumtc.ca
Project-URL: Bug Tracker, https://github.com/Datum-Technology-Corporation/mio_cli_client/issues
Keywords: SystemVerilog,UVM,DV,verilog,VHDL,hdl,rtl,synthesis,FPGA,simulation,Xilinx,Altera
Classifier: Programming Language :: Python :: 3
Classifier: Operating System :: OS Independent
Classifier: Topic :: Utilities
Classifier: Topic :: Software Development :: Build Tools
Requires-Python: >=3.6.8
License-File: LICENSE
Requires-Dist: sphinx-book-theme >=0.2.0
Requires-Dist: zipfile2 >=0.0.12
Requires-Dist: tqdm >=4.63.0
Requires-Dist: Jinja2 >=3.0.3
Requires-Dist: PyYAML >=6.0
Requires-Dist: toml >=0.10.2
Requires-Dist: fusesoc ==1.12.0
Requires-Dist: requests >=2.27.1
Requires-Dist: semver >=2.13.0
Requires-Dist: ezodf >=0.3.2
